PirxcyPinger/__init__.py
MikeyyFTN-2.2.9.dist-info/METADATA
MikeyyFTN-2.2.9.dist-info/WHEEL
MikeyyFTN-2.2.9.dist-info/top_level.txt
MikeyyFTN-2.2.9.dist-info/RECORD
