Metadata-Version: 2.1
Name: MikeyyFTN
Version: 2.2.9
Summary: Async Tool For MikeyyFTN
Home-page: https://pirxcypingerfinal.pirxcyfinal.repl.co/
Author: MikeyyFTN
License: UNKNOWN
Platform: UNKNOWN
Classifier: Programming Language :: Python :: 3
Classifier: License :: OSI Approved :: MIT License
Classifier: Operating System :: OS Independent
Requires-Dist: aiohttp
